dsrag/__init__.py
dsrag/add_document.py
dsrag/auto_context.py
dsrag/auto_query.py
dsrag/create_kb.py
dsrag/custom_term_mapping.py
dsrag/embedding.py
dsrag/knowledge_base.py
dsrag/llm.py
dsrag/metadata.py
dsrag/reranker.py
dsrag/rse.py
dsrag/chat/__init__.py
dsrag/chat/auto_query.py
dsrag/chat/chat.py
dsrag/chat/chat_types.py
dsrag/chat/citations.py
dsrag/chat/instructor_get_response.py
dsrag/chat/model_names.py
dsrag/database/__init__.py
dsrag/database/chat_thread/basic_db.py
dsrag/database/chat_thread/db.py
dsrag/database/chat_thread/sqlite_db.py
dsrag/database/chunk/__init__.py
dsrag/database/chunk/basic_db.py
dsrag/database/chunk/db.py
dsrag/database/chunk/dynamo_db.py
dsrag/database/chunk/postgres_db.py
dsrag/database/chunk/sqlite_db.py
dsrag/database/chunk/types.py
dsrag/database/vector/__init__.py
dsrag/database/vector/basic_db.py
dsrag/database/vector/chroma_db.py
dsrag/database/vector/db.py
dsrag/database/vector/milvus_db.py
dsrag/database/vector/pinecone_db.py
dsrag/database/vector/postgres_db.py
dsrag/database/vector/qdrant_db.py
dsrag/database/vector/types.py
dsrag/database/vector/weaviate_db.py
dsrag/dsparse/__init__.py
dsrag/dsparse/main.py
dsrag/dsparse/file_parsing/__init__.py
dsrag/dsparse/file_parsing/element_types.py
dsrag/dsparse/file_parsing/file_system.py
dsrag/dsparse/file_parsing/non_vlm_file_parsing.py
dsrag/dsparse/file_parsing/vlm.py
dsrag/dsparse/file_parsing/vlm_clients.py
dsrag/dsparse/file_parsing/vlm_file_parsing.py
dsrag/dsparse/models/__init__.py
dsrag/dsparse/models/types.py
dsrag/dsparse/sectioning_and_chunking/__init__.py
dsrag/dsparse/sectioning_and_chunking/chunking.py
dsrag/dsparse/sectioning_and_chunking/semantic_sectioning.py
dsrag/dsparse/utils/__init__.py
dsrag/dsparse/utils/imports.py
dsrag/utils/imports.py
dsrag-0.5.6.dist-info/licenses/LICENSE
dsrag-0.5.6.dist-info/METADATA
dsrag-0.5.6.dist-info/WHEEL
dsrag-0.5.6.dist-info/top_level.txt
dsrag-0.5.6.dist-info/RECORD
