Metadata-Version: 2.4
Name: dsrag
Version: 0.5.6
Summary: State-of-the-art RAG pipeline from D-Star AI
Author-email: Zach McCormick <zach@d-star.ai>, Nick McCormick <nick@d-star.ai>
License-Expression: MIT
Project-URL: Homepage, https://github.com/D-Star-AI/dsRAG
Project-URL: Documentation, https://github.com/D-Star-AI/dsRAG
Project-URL: Contact, https://github.com/D-Star-AI/dsRAG
Classifier: Development Status :: 4 - Beta
Classifier: Intended Audience :: Developers
Classifier: Intended Audience :: Science/Research
Classifier: Operating System :: OS Independent
Classifier: Programming Language :: Python :: 3.9
Classifier: Programming Language :: Python :: 3.10
Classifier: Programming Language :: Python :: 3.11
Classifier: Programming Language :: Python :: 3.12
Classifier: Topic :: Database
Classifier: Topic :: Software Development
Classifier: Topic :: Software Development :: Libraries
Classifier: Topic :: Software Development :: Libraries :: Application Frameworks
Classifier: Topic :: Software Development :: Libraries :: Python Modules
Requires-Python: >=3.9
License-File: LICENSE
Requires-Dist: langchain-text-splitters>=0.3.0
Requires-Dist: langchain-core>=0.3.0
Requires-Dist: pydantic>=2.8.2
Requires-Dist: numpy>=1.20.0
Requires-Dist: pandas>=2.0.0
Requires-Dist: tiktoken>=0.5.0
Requires-Dist: tqdm>=4.65.0
Requires-Dist: requests>=2.30.0
Requires-Dist: python-dotenv>=1.0.0
Requires-Dist: typing-extensions>=4.5.0
Requires-Dist: instructor>=1.7.0
Requires-Dist: scipy>=1.10.0
Requires-Dist: scikit-learn>=1.2.0
Requires-Dist: pillow>=10.0.0
Requires-Dist: pdf2image>=1.16.0
Requires-Dist: docx2txt>=0.8
Requires-Dist: pypdf>=3.0.1
Provides-Extra: faiss
Requires-Dist: faiss-cpu>=1.8.0; extra == "faiss"
Provides-Extra: chroma
Requires-Dist: chromadb>=0.5.5; extra == "chroma"
Provides-Extra: weaviate
Requires-Dist: weaviate-client>=4.6.0; extra == "weaviate"
Provides-Extra: qdrant
Requires-Dist: qdrant-client>=1.8.0; extra == "qdrant"
Provides-Extra: milvus
Requires-Dist: pymilvus>=2.3.5; extra == "milvus"
Provides-Extra: pinecone
Requires-Dist: pinecone>=3.0.0; extra == "pinecone"
Provides-Extra: postgres
Requires-Dist: psycopg2-binary>=2.9.0; extra == "postgres"
Requires-Dist: pgvector>=0.2.0; extra == "postgres"
Provides-Extra: boto3
Requires-Dist: boto3>=1.28.0; extra == "boto3"
Provides-Extra: openai
Requires-Dist: openai>=1.52.2; extra == "openai"
Provides-Extra: cohere
Requires-Dist: cohere>=4.0.0; extra == "cohere"
Provides-Extra: voyageai
Requires-Dist: voyageai>=0.1.0; extra == "voyageai"
Provides-Extra: ollama
Requires-Dist: ollama>=0.1.0; extra == "ollama"
Provides-Extra: anthropic
Requires-Dist: anthropic>=0.37.1; extra == "anthropic"
Provides-Extra: google-generativeai
Requires-Dist: google-generativeai>=0.8.3; extra == "google-generativeai"
Provides-Extra: google-genai
Requires-Dist: google-genai>=0.1.0; extra == "google-genai"
Provides-Extra: all-dbs
Requires-Dist: dsrag[boto3,chroma,faiss,milvus,pinecone,postgres,qdrant,weaviate]; extra == "all-dbs"
Provides-Extra: all-models
Requires-Dist: dsrag[anthropic,cohere,google-genai,google-generativeai,ollama,openai,voyageai]; extra == "all-models"
Provides-Extra: all
Requires-Dist: dsrag[all-dbs,all-models]; extra == "all"
Dynamic: license-file
